{
  "version": "https://jsonfeed.org/version/1.1",
  "title": "Journal — Igor For Men",
  "home_page_url": "https://igorformen.com/blog/",
  "feed_url": "https://igorformen.com/feed.json",
  "items": [
    {
      "id": "https://igorformen.com/blog/rene-21-years-waxing-men-west-hollywood",
      "url": "https://igorformen.com/blog/rene-21-years-waxing-men-west-hollywood",
      "title": "What 21+ Years of Waxing Men Has Taught Rene'",
      "content_text": "Twenty-one years of waxing men has taught Rene' that consistency beats speed, discretion matters more than small talk, and reading skin type in the first sixty seconds determines the entire appointment. Most men arrive nervous and leave surprised the experience was straightforward. The difference between a practitioner who has seen thousands of male clients and one who has seen dozens shows in how they handle the scrotum, apply tension, and adjust wax temperature without asking. Male skin is thicker and produces coarser hair. The pubic region has more surface variation—folds, angles, and tension points that require different hand positions than a standard bikini line. A practitioner learns these adjustments over years, not weeks. Rene' has performed over fifteen thousand male waxing appointments in West Hollywood, most of them Brazilian services or back waxing. That volume builds muscle memory. The wax goes on at the right thickness. The pull happens at the right angle. The client feels pressure, not pain. Experience also means knowing when to stop. Some men have skin that reddens easily or a low pain threshold that shows up halfway through the appointment. A practitioner with two decades of work knows how to pace the session, offer a break, or adjust the wax formula without making the client feel like they failed. Discretion is part of the skill set. Men return because they trust the practitioner will not rush them or make them feel exposed. Men in West Hollywood, Beverly Hills, and Mid-City arrive with specific expectations. They want privacy. They want the appointment to start on time. They want the practitioner to explain what will happen without making them ask. Rene' has noticed that first-time clients often apologize for being nervous. Repeat clients walk in, undress, and lie down without hesitation. The shift happens after one or two appointments. Trust builds faster when the environment stays consistent—same practitioner, same suite, same process. Most men book their first Brazilian after a friend mentions it or after reading about the service online. They arrive with questions they do not ask out loud. A practitioner with experience answers those questions through action. The wax goes on. The wax comes off. The skin looks clean. The client realizes the process is clinical, not awkward. Repeat bookings follow. West Hollywood clients also value discretion. The salon is located on Larrabee Street, a quiet block near the Pacific Design Center. Appointments are private. No one sees you enter or leave. No one makes small talk in a waiting room. This model works because men who seek waxing services want efficiency and privacy, not a social experience. > \"I have waxed the same clients for over a decade. They return because the result is consistent and the appointment is private. That is what experience delivers—no surprises, no variation.\" > — Rene', practitioner Applying wax to the scrotum requires one hand to stretch the skin and the other to apply a thin, even layer. The wax must harden in seconds. The pull must happen in one motion, against the direction of growth, with the skin held taut. A practitioner learns this through repetition. Rene' estimates that the average male Brazilian involves thirty to forty individual wax applications. Multiply that by fifteen thousand appointments and the skill becomes automatic. The same principle applies to back waxing and chest work. Coarse hair requires hard wax, which adheres to the hair shaft rather than the skin. The wax must be warm enough to spread but cool enough to harden quickly. A practitioner adjusts the temperature by feel, not by thermometer. This is a skill that develops after thousands of hours in the same room with the same tools. Experience also means knowing which clients will develop ingrown hairs and which will not. Skin type, hair texture, and how tightly the follicle grips the hair all play a role. Rene' can predict within the first few minutes whether a client will need to follow the aftercare guide strictly or whether their skin will heal without issue. This is not intuition—it is pattern recognition built over two decades. Men assume that a top-rated practitioner works faster. The opposite is true. Speed increases the chance of breakage, missed spots, and skin irritation. Rene' takes the same amount of time for every Brazilian—thirty to forty-five minutes. The goal is complete hair removal with minimal redness. Rushing compromises both. Clients also assume that a practitioner with twenty-one years of experience charges more. At Igor For Men, pricing reflects the private setting and appointment-only model, not years of experience. The male Brazilian starts at $145+, which is competitive with other private salons near the Sunset Strip and Beverly Center. The value is consistency, not markup. Another misunderstanding: men think that an experienced practitioner will make the process painless. Waxing removes hair from the root. That creates a …",
      "date_published": "2026-05-18T12:00:00-08:00"
    },
    {
      "id": "https://igorformen.com/blog/aftercare-72-hours-male-brazilian",
      "url": "https://igorformen.com/blog/aftercare-72-hours-male-brazilian",
      "title": "Aftercare Hour-by-Hour: 0–72 Hours After Your Brazilian",
      "content_text": "The best aftercare for a male Brazilian wax follows a strict timeline: cool the skin in the first 24 hours, avoid friction and heat, wear loose cotton, and start gentle exfoliation on day three. Most redness fades within 12 hours. Bumps or ingrowns appear between days two and five if you skip exfoliation or wear tight clothing too soon. Leave the salon and go straight home if possible. Your skin is open at the follicle level. Avoid the gym, public pools, and steam rooms for at least 24 hours. Wear loose cotton underwear or athletic shorts. No denim. No compression fabric. Apply a cold compress if you feel heat or see redness. A damp washcloth from the fridge works. Hold it on the waxed area for five minutes, then let the skin breathe. Do not apply lotion, oil, or fragrance in the first six hours. The follicles are still closing. Skip the shower if you can wait. If you must rinse, use lukewarm water and no soap on the waxed area. Pat dry with a clean towel. Do not rub. This is the window when most irritation develops. Do not take a hot shower, sit in a sauna, or use a heating pad. Heat dilates blood vessels and can trigger inflammation or small red bumps. Sleep in loose cotton or nothing. If you sleep on your stomach, put a clean towel under your hips. Change your sheets the night of your Brazilian service — fresh linen reduces bacteria contact. Avoid sexual activity for 24 hours minimum. Friction on freshly waxed skin can cause micro-abrasions or ingrown hairs. If you live in West Hollywood and walk or bike, plan your appointment for an evening when you can stay home afterward. > \"Men who follow the 24-hour cooling rule see almost no bumps. The ones who go to the gym that same night or wear tight jeans always call back with questions.\" > — Rene', practitioner After 24 hours, you can shower normally. Use a mild, unscented body wash. Avoid anything with alcohol, fragrance, or exfoliating beads. Rinse thoroughly. Pat the area dry and apply a thin layer of unscented lotion or aloe gel. Look for products with glycerin or hyaluronic acid. These pull moisture into the skin without clogging follicles. Apply twice a day — morning and night. You can return to light activity. A walk along Santa Monica Boulevard or a short session at the gym is fine. Wear moisture-wicking fabric, not cotton, if you plan to sweat. Shower immediately after and reapply lotion. Do not exfoliate yet. The skin is still settling. Wait until hour 72. This is when you begin the routine that prevents ingrown hairs. Use a gentle physical exfoliant — a soft washcloth, a konjac sponge, or a body scrub with fine grains. Exfoliate in the shower using small circular motions. Cover the entire waxed area, including the shaft, scrotum, and space between the buttocks. Exfoliate every other day for the first two weeks, then twice a week after that. This lifts dead skin cells and clears the path for new hair to grow straight out of the follicle. Most ingrowns form because the hair curls back under a layer of dead skin. If you see small red bumps at this stage, they are likely early ingrowns. Do not pick or squeeze. Exfoliate gently and apply a product with salicylic acid or glycolic acid at night. The bumps usually flatten within three days. You can resume all normal activity by hour 72, including sexual contact, hot yoga, or swimming. If you visit the Pacific Design Center or work out near Beverly Hills, bring a change of clothes so you are not sitting in damp fabric. Do not use retinol, benzoyl peroxide, or any prescription acne treatment on the waxed area. These products thin the skin and increase sensitivity. If you use them on your face, keep them there. Do not shave between waxing appointments. Shaving disrupts the hair growth cycle and makes your next wax more painful. If you need a touch-up before your next visit to our West Hollywood salon, trim with scissors. Do not apply deodorant, body spray, or cologne to the waxed area. Alcohol-based products sting and can trigger a rash. Avoid tight underwear, jockstraps, or shapewear for the full 72 hours. Compression traps heat and bacteria. Loose cotton or modal fabric is the safest choice.",
      "date_published": "2026-05-15T12:00:00-08:00"
    },
    {
      "id": "https://igorformen.com/blog/brazilian-vs-manzilian-difference",
      "url": "https://igorformen.com/blog/brazilian-vs-manzilian-difference",
      "title": "Brazilian vs Manzilian: What is the Difference?",
      "content_text": "A Brazilian wax and a Manzilian are the same service. Both remove all hair from the pubic region, including the shaft, scrotum, and area between the buttocks. \"Manzilian\" is a marketing term that emerged in the mid-2000s to signal the service was designed for men. Most salons in West Hollywood now use \"male Brazilian\" or simply \"Brazilian\" regardless of gender. The procedure, technique, and result are identical. The word \"Brazilian\" describes the scope of hair removal—everything from the pubic bone to the tailbone. It originated in New York in the 1980s when the J Sisters salon introduced the style. The service became standard in women's salons and later adapted for men without changing the technique. \"Manzilian\" appeared around 2005 as salons began marketing intimate waxing to male clients. The portmanteau combined \"man\" and \"Brazilian\" to make the service feel less gendered. Some men preferred the term because it signaled the practitioner understood male anatomy. Others found it unnecessary. By the 2010s, most licensed estheticians dropped the distinction. A male Brazilian wax at Igor For Men on Larrabee Street in West Hollywood uses the same hard wax, same positioning, and same aftercare whether you call it a Brazilian or Manzilian. The terms now function as synonyms. If a salon lists both on its menu, the services are the same. If it lists only one, ask—but expect the same scope of removal. The appointment takes 30–45 minutes in a private suite. You undress from the waist down and lie on a cushioned table. The practitioner applies hard wax in sections—front, underside, and between. The wax hardens in seconds and lifts off without strips. Hair comes out at the root. Positioning varies by area. For the front, you lie on your back with knees bent. For the underside and scrotum, you may hold skin taut or shift to your side. For the area between the buttocks, you turn onto your stomach or pull one knee toward your chest. The practitioner works quickly and adjusts as needed. > \"Men ask if there's a difference between a Brazilian and Manzilian. There isn't. The wax goes where the hair is. The name doesn't change the technique.\" > — Rene', practitioner Most men describe the sensation as sharp but brief. The first pass is the most intense. Subsequent appointments hurt less as hair grows back finer. Redness fades within a few hours. Results last three to five weeks depending on your hair cycle. Marketing language creates the impression that men's services require different products or methods. In reality, male and female anatomy differ in surface area and skin texture, but the wax formula and removal process stay the same. Hard wax works on coarse hair regardless of where it grows. Some salons in Beverly Hills and West Hollywood still use \"Manzilian\" on their menus to clarify that the service accommodates male clients. This signals that the practitioner is trained in male anatomy and comfortable with the procedure. It does not mean the wax is different or the appointment follows a separate protocol. Other salons list only \"Brazilian\" and note in the description that the service is available for all clients. Both approaches describe the same removal scope. If you book a Brazilian at a salon that serves men, you receive full intimate waxing. If you book a Manzilian, you receive the same thing. The confusion also stems from online forums where men debate which term sounds less awkward. The answer depends on personal preference. Neither term changes what happens in the appointment. When scheduling your first Brazilian service, confirm the scope of removal. Ask if the appointment includes the pubic area, shaft, scrotum, and area between the buttocks. Most salons define this as \"full Brazilian\" or \"complete Brazilian.\" Some offer a \"modified Brazilian\" that stops short of the tailbone. Clarify which version you want. Ask about the wax type. Hard wax adheres to hair rather than skin and reduces irritation on sensitive areas. Strip wax (soft wax) is faster but pulls at the skin and causes more discomfort. Most West Hollywood salons use hard wax for intimate areas. Confirm the practitioner's experience with male clients. At Igor For Men, Rene' has over 21 years of experience and works in a private suite on Larrabee Street near the Sunset Strip. The appointment is discreet and follows the same protocol whether you call it a Brazilian or Manzilian. Ask about pre-appointment requirements. Hair should be at least a quarter-inch long—about three weeks of growth. Trim if it's longer than half an inch. Shower before your appointment and avoid caffeine, which tightens skin and increases sensitivity. For pricing, expect to pay $145 to $200 in Los Angeles depending on the salon and location. Rates in West Hollywood and Beverly Hills tend toward the higher end due to real estate costs and practitioner experience. The full-body trimming service is a separate option if you prefer to maintain length rather than remove hair entirely.",
      "date_published": "2026-05-11T12:00:00-08:00"
    },
    {
      "id": "https://igorformen.com/blog/mens-waxing-west-hollywood-guide",
      "url": "https://igorformen.com/blog/mens-waxing-west-hollywood-guide",
      "title": "Men's Waxing in West Hollywood: Complete 2026 Guide",
      "content_text": "Men's waxing in West Hollywood covers Brazilian, back, chest, arm, leg, and eyebrow services performed by licensed estheticians in private settings. Appointments run 30–60 minutes depending on the area. Most salons use hard wax, which adheres to hair rather than skin and reduces irritation. Pricing starts around $65 for eyebrows and reaches $195+ for full legs or combined areas. West Hollywood salons offer targeted and full-body options. The male Brazilian wax removes hair from the pubic area, underside, and between. A back wax service covers the full back or upper/lower sections. Chest and abdomen waxing treats the torso in one appointment. Arm and leg waxing address limbs from shoulder to wrist or hip to ankle. Eyebrow shaping refines the brow line without changing the natural arch. Full-body trimming uses clippers to reduce length across multiple zones in a single session. This service suits men who want uniform grooming without complete removal. Sessions are priced hourly and customized to your preference. Most salons near the Sunset Strip and Robertson Boulevard operate by appointment only. Walk-ins are rare. Book 48 hours ahead during weekdays and up to a week ahead on weekends. Hard wax is the standard for men's services. The practitioner applies warm wax to a small section, lets it harden for a few seconds, then lifts it off in one motion. No strips are involved. The wax grips the hair shaft and pulls it from the root. Skin is held taut during removal to minimize discomfort. A Brazilian takes 30–45 minutes. Back waxing runs 20–30 minutes. Chest and abdomen take 30–40 minutes. Legs require 45–60 minutes for both limbs. You undress only in the area being treated and lie on a cushioned table in a private suite. Hair should be at least a quarter-inch long—about three weeks of growth from the last shave. Shorter hair won't lift cleanly. Longer hair can be trimmed before waxing begins. > \"Men expect waxing to hurt more than it does. The first pass is sharp, but most clients settle in after that. Hard wax makes a difference—it's gentler on skin than strip wax, and we work quickly.\" > — Rene', practitioner Waxing removes hair at the root, so regrowth takes three to five weeks. Shaving cuts hair at the surface and regrowth appears in days. Trimming reduces length but doesn't remove hair, so maintenance is weekly or more frequent. Waxed skin stays smooth longer. There's no stubble phase and no razor burn. Regrowth is finer over time because the hair follicle weakens with repeated removal. After several appointments, many men notice slower and sparser growth. Athletes and performers choose waxing for definition. Smooth skin shows muscle contour and reduces friction during movement. Men in Beverly Hills and Mid-City book regular appointments to maintain results without daily upkeep. Waxing also eliminates ingrown hairs that come from shaving against the grain. The removal process exfoliates dead skin, which keeps follicles clear and reduces bumps. Privacy matters. Look for salons with individual suites rather than open treatment areas. Appointment-only models ensure you won't overlap with other clients in the waiting area. Discreet entrances and private parking are common near Larrabee Street and Santa Monica Boulevard. Practitioner experience is the next factor. Ask how long the esthetician has performed men's waxing specifically. Technique varies between male and female clients due to hair texture and skin sensitivity. A practitioner with a decade or more of experience works faster and with less discomfort. Wax quality affects results. Hard wax should be European-grade and applied at the right temperature—warm enough to spread thinly but not hot enough to burn. Salons that use pre-made strips or sugar wax may not deliver the same clean removal on coarse hair. Hygiene is non-negotiable. Single-use applicators, fresh linens, and sanitized surfaces are standard. The suite should smell neutral, not chemically sharp. If a salon reuses spatulas or leaves wax pots uncovered, leave. Location convenience extends your consistency. A private West Hollywood salon within a seven-minute drive from Beverly Hills or Fairfax makes it easier to keep a standing appointment. Parking should be simple and off-street. Eyebrow waxing starts around $65. A male Brazilian begins at $145. Back waxing runs $145 and up. Chest and abdomen services start at $145. Full legs begin at $195. Arms start at $145. Full-body trimming is priced at $150 per hour and covers multiple zones in one session. Prices reflect the practitioner's experience, the salon's overhead, and the service model. Private suites cost more to operate than open spa floors. Appointment-only salons near the Pacific Design Center and The Abbey charge premium rates because they limit daily bookings and offer longer windows per client. Add-ons increase the total. Some salons offer post-wax serums, exfoliating treatments, or numbing creams for an extra fee. Most include basic af…",
      "date_published": "2026-05-08T12:00:00-08:00"
    },
    {
      "id": "https://igorformen.com/blog/male-brazilian-cost-los-angeles-2026",
      "url": "https://igorformen.com/blog/male-brazilian-cost-los-angeles-2026",
      "title": "How Much Does a Male Brazilian Wax Cost in LA? (2026 Pricing Guide)",
      "content_text": "A male Brazilian wax in Los Angeles typically starts at $145 and can reach $200 or more depending on the salon, practitioner experience, and service model. At Igor For Men in West Hollywood, the service begins at $145+ and includes a private suite, hard wax application, and a practitioner with over 21 years of experience. Prices reflect the appointment-only model and discreet setting on Larrabee Street. Three factors determine what you pay: practitioner expertise, wax type, and salon overhead. A practitioner with two decades of experience charges more than a recent graduate because technique matters. Hard wax costs more to source than soft wax, but it adheres to hair rather than skin and reduces irritation. Private suites in West Hollywood or Beverly Hills carry higher rent than shared spaces in Mid-City, and that cost appears in the service price. Walk-in chains often advertise lower rates because they operate on volume. You may wait in a lobby with other clients, and the practitioner may see eight to ten people in a shift. Appointment-only salons limit daily bookings to ensure each client receives focused attention. That model costs more to run, so the service price reflects it. Location also plays a role. A salon near the Sunset Strip or Robertson Boulevard pays more in rent than one in a strip mall east of Fairfax. You are not paying for the zip code alone—you are paying for proximity, privacy, and the ability to book a time that works without competing for availability. The male Brazilian wax at IFM takes 30 to 45 minutes and covers the front, underside, and area between. You undress from the waist down in a private suite, lie on a cushioned table, and the practitioner applies hard wax in sections. The wax hardens in seconds and lifts off without strips. Each section is treated once, and the practitioner works methodically to minimize discomfort. The service includes a post-wax gel to calm the skin and a brief review of aftercare guidelines. You receive specific instructions about showering, exfoliation, and when to reschedule. The practitioner answers questions during the appointment, not after you leave. Pricing starts at $145+ because the service is performed by Rene', who has refined his technique over 21 years. The salon operates Tuesday through Saturday from 8 AM to 6 PM, and every appointment is booked in advance. Walk-ins are not accepted. This structure allows the practitioner to prepare the suite, review your intake form, and dedicate the full appointment window to you. > \"Men often ask why the price is higher than a chain. The answer is time and attention. I see four to five clients a day, not twelve. Each appointment gets the full window, and I do not rush.\" > — Rene', practitioner A male Brazilian wax in Los Angeles ranges from $90 at budget chains to $200+ at luxury spas. IFM sits in the middle-to-upper band at $145+ because the service is performed by a single practitioner in a private setting. You are not assigned to whoever is available that day. You book with Rene', and Rene' performs the service. Chains in Hollywood or the Westside advertise lower prices but often add fees for hard wax, extended time, or specific areas. The advertised rate may cover a basic service, and you learn about additional charges when you arrive. IFM publishes one starting price and does not add fees for wax type or technique. The $145+ rate includes everything described in the service overview. Luxury spas near Beverly Hills or Century City charge $175 to $200+ for a male Brazilian. Those rates often include amenities like steam rooms, robes, or post-service lounges. IFM does not offer those amenities because the focus is the wax itself. The suite is private, the table is clean, and the practitioner is experienced. You are paying for the service, not the extras. Men who prioritize discretion and consistency choose appointment-only salons. Men who prioritize cost choose chains. Neither choice is wrong, but the experience differs. At IFM, you will not sit in a waiting room with other clients, and you will not be handed off to a different practitioner each visit. IFM operates by appointment only, which means the salon does not generate revenue during open hours between bookings. A walk-in model fills those gaps with clients who arrive without notice. An appointment-only model leaves gaps intentionally to give each client space and to allow the practitioner time to reset the suite. This structure costs more to maintain because the practitioner cannot maximize the number of clients per day. The trade-off is focus. When you book an appointment at IFM, you receive the full time slot. The practitioner does not cut the service short to accommodate the next client, and you do not feel rushed. The salon is located at 801 Larrabee Street in West Hollywood, a seven-minute drive from the Beverly Center and walking distance from the Pacific Design Center. Rent in this area is higher than in neighborhoods farther east, and…",
      "date_published": "2026-05-07T12:00:00-08:00"
    },
    {
      "id": "https://igorformen.com/blog/first-male-brazilian-west-hollywood",
      "url": "https://igorformen.com/blog/first-male-brazilian-west-hollywood",
      "title": "Your First Male Brazilian in West Hollywood: A Discreet Walk-Through",
      "content_text": "A first-time male Brazilian wax takes 30–45 minutes in a private suite. You undress from the waist down, lie on a cushioned table, and the practitioner applies hard wax in sections—front, underside, and between. The wax hardens in seconds and lifts off without strips. Most men describe the sensation as sharp but brief, and easier than they expected. Book your appointment at least 48 hours out. Hair should be a quarter-inch long—about three weeks of growth if you shave, two if you trim. Shower that morning and skip lotions or oils; clean, dry skin lets wax grip hair, not skin. Wear loose cotton briefs and soft pants for the drive home. IFM is on Larrabee Street in West Hollywood, a quiet block north of Santa Monica Boulevard. You enter through a discreet street-level door. No waiting room full of strangers—your practitioner meets you in the suite. You undress from the waist down and lie on a padded table covered with fresh paper. A towel drapes your midsection until the practitioner begins. Rene' works in a sequence: pubic mound, shaft and scrotum, underside, and finally the area between the cheeks. He applies wax with a wooden spatula, waits a few seconds for it to set, then lifts it off in one motion against the direction of growth. The process is methodical. Rene' asks you to hold skin taut in certain areas or shift position—knees bent, then one leg up, then the other. He works quickly. The entire Brazilian service runs 30 to 45 minutes depending on hair density and your comfort level. > \"In 21 years I've seen every body type and every level of nerves. The men who do best are the ones who breathe normally and don't clench. Tension makes everything harder.\" > — Rene', practitioner Pain is subjective. Most men say the pubic mound stings the most because the skin is thinner and hair is coarser. The scrotum and perianal area feel sharper but briefer—fewer nerve endings, thinner hair. Between pulls, the practitioner trims stray hairs with scissors and tweezers any the wax missed. By the end, you are completely smooth. Your skin will be red and slightly raised for two to four hours. That is normal. The redness fades fastest if you avoid tight clothing and hot water the rest of the day. Some men feel a dull tenderness, like a sunburn. Others feel nothing at all. Do not apply deodorant, cologne, or scented lotion to the waxed area for 24 hours. Fragrance and alcohol irritate open follicles. Stick to unscented aloe or the post-wax serum Rene' recommends. Sleep in loose boxers the first night. Ingrown hairs appear in about 30 percent of first-timers, usually three to five days later. They look like small red bumps. Exfoliate gently with a washcloth starting 48 hours after your appointment, and the bumps clear within a week. Our aftercare guide covers this in detail. Discretion matters. West Hollywood has a long history of private, judgment-free grooming services. IFM is by appointment only—no walk-ins, no overlapping clients. The suite is soundproofed. The entrance is unmarked. Your practitioner has worked with thousands of men, from first-timers to regulars who have waxed for years. The location also makes logistics simple. IFM is a seven-minute drive from Beverly Hills, ten from Mid-City, and walkable from much of the Sunset Strip. Street parking on Larrabee Street is usually open, and the Pacific Design Center garage is two blocks south. Bring nothing but yourself and loose clothing. You do not need to bring wipes, numbing cream, or pain relievers. The practitioner has everything required. If you want to take ibuprofen beforehand, take it 30 minutes before your appointment—but most men find it unnecessary. Skip the gym that morning. Sweat and friction increase sensitivity. Skip caffeine if you are prone to jitters; adrenaline amplifies sensation. Do not drink alcohol before the appointment. It thins blood and makes you more likely to bruise. If you are nervous, say so. Rene' adjusts his pace and gives you breaks between sections. There is no timer. The appointment takes as long as it takes.",
      "date_published": "2026-05-06T12:00:00-08:00"
    }
  ]
}